{
  "XRPUSDTPERP": {
    "cycle_count": 102442,
    "current_phase": 1,
    "maker_account": "CM1",
    "maker_side": "BUY",
    "last_cycle_time": "2026-04-11T22:59:58.810502970+00:00",
    "total_trades": 102442,
    "external_fills": 0
  },
  "ETHUSDTPERP": {
    "cycle_count": 102458,
    "current_phase": 0,
    "maker_account": "CM1",
    "maker_side": "BUY",
    "last_cycle_time": "2026-04-11T22:59:58.831412474+00:00",
    "total_trades": 102458,
    "external_fills": 0
  },
  "DOGEUSDTPERP": {
    "cycle_count": 102452,
    "current_phase": 0,
    "maker_account": "CM1",
    "maker_side": "BUY",
    "last_cycle_time": "2026-04-11T22:59:58.841530919+00:00",
    "total_trades": 102452,
    "external_fills": 0
  },
  "BTCUSDTPERP": {
    "cycle_count": 102450,
    "current_phase": 0,
    "maker_account": "CM1",
    "maker_side": "BUY",
    "last_cycle_time": "2026-04-11T22:59:58.820716243+00:00",
    "total_trades": 102450,
    "external_fills": 0
  },
  "SOLUSDTPERP": {
    "cycle_count": 102471,
    "current_phase": 1,
    "maker_account": "CM1",
    "maker_side": "BUY",
    "last_cycle_time": "2026-04-11T22:59:58.800055795+00:00",
    "total_trades": 102471,
    "external_fills": 0
  },
  "AVAXUSDTPERP": {
    "cycle_count": 102435,
    "current_phase": 1,
    "maker_account": "CM1",
    "maker_side": "BUY",
    "last_cycle_time": "2026-04-11T22:59:58.788427142+00:00",
    "total_trades": 102435,
    "external_fills": 0
  }
}