{
  "BTCUSDTPERP": {
    "cycle_count": 88709,
    "current_phase": 1,
    "maker_account": "CM1",
    "maker_side": "BUY",
    "last_cycle_time": "2026-04-09T12:49:49.401704870+00:00",
    "total_trades": 88709,
    "external_fills": 0
  },
  "SOLUSDTPERP": {
    "cycle_count": 88731,
    "current_phase": 1,
    "maker_account": "CM1",
    "maker_side": "BUY",
    "last_cycle_time": "2026-04-09T12:49:49.375800794+00:00",
    "total_trades": 88731,
    "external_fills": 0
  },
  "ETHUSDTPERP": {
    "cycle_count": 88713,
    "current_phase": 1,
    "maker_account": "CM1",
    "maker_side": "BUY",
    "last_cycle_time": "2026-04-09T12:49:49.413940741+00:00",
    "total_trades": 88713,
    "external_fills": 0
  },
  "XRPUSDTPERP": {
    "cycle_count": 88702,
    "current_phase": 1,
    "maker_account": "CM1",
    "maker_side": "BUY",
    "last_cycle_time": "2026-04-09T12:49:49.388451732+00:00",
    "total_trades": 88702,
    "external_fills": 0
  },
  "DOGEUSDTPERP": {
    "cycle_count": 88705,
    "current_phase": 0,
    "maker_account": "CM1",
    "maker_side": "BUY",
    "last_cycle_time": "2026-04-09T12:49:49.426396061+00:00",
    "total_trades": 88705,
    "external_fills": 0
  },
  "AVAXUSDTPERP": {
    "cycle_count": 88697,
    "current_phase": 1,
    "maker_account": "CM1",
    "maker_side": "BUY",
    "last_cycle_time": "2026-04-09T12:49:49.363033954+00:00",
    "total_trades": 88697,
    "external_fills": 0
  }
}