{
  "AVAXUSDTPERP": {
    "cycle_count": 87288,
    "current_phase": 0,
    "maker_account": "CM1",
    "maker_side": "BUY",
    "last_cycle_time": "2026-04-09T06:54:59.442607880+00:00",
    "total_trades": 87288,
    "external_fills": 0
  },
  "BTCUSDTPERP": {
    "cycle_count": 87300,
    "current_phase": 0,
    "maker_account": "CM1",
    "maker_side": "BUY",
    "last_cycle_time": "2026-04-09T06:54:59.481440918+00:00",
    "total_trades": 87300,
    "external_fills": 0
  },
  "ETHUSDTPERP": {
    "cycle_count": 87304,
    "current_phase": 1,
    "maker_account": "CM1",
    "maker_side": "BUY",
    "last_cycle_time": "2026-04-09T06:54:59.494117154+00:00",
    "total_trades": 87304,
    "external_fills": 0
  },
  "XRPUSDTPERP": {
    "cycle_count": 87293,
    "current_phase": 1,
    "maker_account": "CM1",
    "maker_side": "BUY",
    "last_cycle_time": "2026-04-09T06:54:59.467900360+00:00",
    "total_trades": 87293,
    "external_fills": 0
  },
  "SOLUSDTPERP": {
    "cycle_count": 87322,
    "current_phase": 1,
    "maker_account": "CM1",
    "maker_side": "BUY",
    "last_cycle_time": "2026-04-09T06:54:59.454977675+00:00",
    "total_trades": 87322,
    "external_fills": 0
  },
  "DOGEUSDTPERP": {
    "cycle_count": 87296,
    "current_phase": 0,
    "maker_account": "CM1",
    "maker_side": "BUY",
    "last_cycle_time": "2026-04-09T06:54:59.506802999+00:00",
    "total_trades": 87296,
    "external_fills": 0
  }
}