{
  "AVAXUSDTPERP": {
    "cycle_count": 101123,
    "current_phase": 1,
    "maker_account": "CM1",
    "maker_side": "BUY",
    "last_cycle_time": "2026-04-11T17:29:49.257503430+00:00",
    "total_trades": 101123,
    "external_fills": 0
  },
  "ETHUSDTPERP": {
    "cycle_count": 101146,
    "current_phase": 1,
    "maker_account": "CM1",
    "maker_side": "BUY",
    "last_cycle_time": "2026-04-11T17:29:49.297521703+00:00",
    "total_trades": 101146,
    "external_fills": 0
  },
  "XRPUSDTPERP": {
    "cycle_count": 101130,
    "current_phase": 0,
    "maker_account": "CM1",
    "maker_side": "BUY",
    "last_cycle_time": "2026-04-11T17:29:49.277779223+00:00",
    "total_trades": 101130,
    "external_fills": 0
  },
  "SOLUSDTPERP": {
    "cycle_count": 101159,
    "current_phase": 1,
    "maker_account": "CM1",
    "maker_side": "BUY",
    "last_cycle_time": "2026-04-11T17:29:49.267190599+00:00",
    "total_trades": 101159,
    "external_fills": 0
  },
  "DOGEUSDTPERP": {
    "cycle_count": 101140,
    "current_phase": 1,
    "maker_account": "CM1",
    "maker_side": "BUY",
    "last_cycle_time": "2026-04-11T17:29:49.307356831+00:00",
    "total_trades": 101140,
    "external_fills": 0
  },
  "BTCUSDTPERP": {
    "cycle_count": 101138,
    "current_phase": 0,
    "maker_account": "CM1",
    "maker_side": "BUY",
    "last_cycle_time": "2026-04-11T17:29:49.287571125+00:00",
    "total_trades": 101138,
    "external_fills": 0
  }
}