{
  "AVAXUSDTPERP": {
    "cycle_count": 140591,
    "current_phase": 1,
    "maker_account": "CM1",
    "maker_side": "BUY",
    "last_cycle_time": "2026-04-18T16:34:46.947160177+00:00",
    "total_trades": 140591,
    "external_fills": 0
  },
  "BTCUSDTPERP": {
    "cycle_count": 140600,
    "current_phase": 0,
    "maker_account": "CM1",
    "maker_side": "BUY",
    "last_cycle_time": "2026-04-18T16:34:46.896315309+00:00",
    "total_trades": 140600,
    "external_fills": 0
  },
  "ETHUSDTPERP": {
    "cycle_count": 140610,
    "current_phase": 0,
    "maker_account": "CM1",
    "maker_side": "BUY",
    "last_cycle_time": "2026-04-18T16:34:46.908543539+00:00",
    "total_trades": 140610,
    "external_fills": 0
  },
  "SOLUSDTPERP": {
    "cycle_count": 140623,
    "current_phase": 0,
    "maker_account": "CM1",
    "maker_side": "BUY",
    "last_cycle_time": "2026-04-18T16:34:46.935581952+00:00",
    "total_trades": 140623,
    "external_fills": 0
  },
  "DOGEUSDTPERP": {
    "cycle_count": 140607,
    "current_phase": 1,
    "maker_account": "CM1",
    "maker_side": "BUY",
    "last_cycle_time": "2026-04-18T16:34:46.922056879+00:00",
    "total_trades": 140607,
    "external_fills": 0
  },
  "XRPUSDTPERP": {
    "cycle_count": 140605,
    "current_phase": 0,
    "maker_account": "CM1",
    "maker_side": "BUY",
    "last_cycle_time": "2026-04-18T16:34:46.959449216+00:00",
    "total_trades": 140605,
    "external_fills": 0
  }
}