{
  "AVAXUSDTPERP": {
    "cycle_count": 133533,
    "current_phase": 1,
    "maker_account": "CM1",
    "maker_side": "BUY",
    "last_cycle_time": "2026-04-17T10:24:58.246243038+00:00",
    "total_trades": 133533,
    "external_fills": 0
  },
  "BTCUSDTPERP": {
    "cycle_count": 133546,
    "current_phase": 1,
    "maker_account": "CM1",
    "maker_side": "BUY",
    "last_cycle_time": "2026-04-17T10:24:58.208030801+00:00",
    "total_trades": 133546,
    "external_fills": 0
  },
  "DOGEUSDTPERP": {
    "cycle_count": 133552,
    "current_phase": 1,
    "maker_account": "CM1",
    "maker_side": "BUY",
    "last_cycle_time": "2026-04-17T10:24:58.226775699+00:00",
    "total_trades": 133552,
    "external_fills": 0
  },
  "ETHUSDTPERP": {
    "cycle_count": 133556,
    "current_phase": 0,
    "maker_account": "CM1",
    "maker_side": "BUY",
    "last_cycle_time": "2026-04-17T10:24:58.217117442+00:00",
    "total_trades": 133556,
    "external_fills": 0
  },
  "SOLUSDTPERP": {
    "cycle_count": 133568,
    "current_phase": 0,
    "maker_account": "CM1",
    "maker_side": "BUY",
    "last_cycle_time": "2026-04-17T10:24:58.236555830+00:00",
    "total_trades": 133568,
    "external_fills": 0
  },
  "XRPUSDTPERP": {
    "cycle_count": 133544,
    "current_phase": 0,
    "maker_account": "CM1",
    "maker_side": "BUY",
    "last_cycle_time": "2026-04-17T10:24:58.256302652+00:00",
    "total_trades": 133544,
    "external_fills": 0
  }
}