{
  "AVAXUSDTPERP": {
    "cycle_count": 86612,
    "current_phase": 0,
    "maker_account": "CM1",
    "maker_side": "BUY",
    "last_cycle_time": "2026-04-09T04:04:48.102260179+00:00",
    "total_trades": 86612,
    "external_fills": 0
  },
  "XRPUSDTPERP": {
    "cycle_count": 86617,
    "current_phase": 0,
    "maker_account": "CM1",
    "maker_side": "BUY",
    "last_cycle_time": "2026-04-09T04:04:48.125761622+00:00",
    "total_trades": 86617,
    "external_fills": 0
  },
  "BTCUSDTPERP": {
    "cycle_count": 86624,
    "current_phase": 0,
    "maker_account": "CM1",
    "maker_side": "BUY",
    "last_cycle_time": "2026-04-09T04:04:48.137456601+00:00",
    "total_trades": 86624,
    "external_fills": 0
  },
  "DOGEUSDTPERP": {
    "cycle_count": 86620,
    "current_phase": 1,
    "maker_account": "CM1",
    "maker_side": "BUY",
    "last_cycle_time": "2026-04-09T04:04:48.161154099+00:00",
    "total_trades": 86620,
    "external_fills": 0
  },
  "SOLUSDTPERP": {
    "cycle_count": 86646,
    "current_phase": 0,
    "maker_account": "CM1",
    "maker_side": "BUY",
    "last_cycle_time": "2026-04-09T04:04:48.114102591+00:00",
    "total_trades": 86646,
    "external_fills": 0
  },
  "ETHUSDTPERP": {
    "cycle_count": 86628,
    "current_phase": 0,
    "maker_account": "CM1",
    "maker_side": "BUY",
    "last_cycle_time": "2026-04-09T04:04:48.149225939+00:00",
    "total_trades": 86628,
    "external_fills": 0
  }
}