{
  "AVAXUSDTPERP": {
    "cycle_count": 128830,
    "current_phase": 1,
    "maker_account": "CM1",
    "maker_side": "BUY",
    "last_cycle_time": "2026-04-16T14:39:58.671335015+00:00",
    "total_trades": 128830,
    "external_fills": 0
  },
  "XRPUSDTPERP": {
    "cycle_count": 128841,
    "current_phase": 1,
    "maker_account": "CM1",
    "maker_side": "BUY",
    "last_cycle_time": "2026-04-16T14:39:58.684488354+00:00",
    "total_trades": 128841,
    "external_fills": 0
  },
  "ETHUSDTPERP": {
    "cycle_count": 128854,
    "current_phase": 1,
    "maker_account": "CM1",
    "maker_side": "BUY",
    "last_cycle_time": "2026-04-16T14:39:58.629960449+00:00",
    "total_trades": 128854,
    "external_fills": 0
  },
  "BTCUSDTPERP": {
    "cycle_count": 128844,
    "current_phase": 0,
    "maker_account": "CM1",
    "maker_side": "BUY",
    "last_cycle_time": "2026-04-16T14:39:58.616763526+00:00",
    "total_trades": 128844,
    "external_fills": 0
  },
  "SOLUSDTPERP": {
    "cycle_count": 128866,
    "current_phase": 1,
    "maker_account": "CM1",
    "maker_side": "BUY",
    "last_cycle_time": "2026-04-16T14:39:58.658142048+00:00",
    "total_trades": 128866,
    "external_fills": 0
  },
  "DOGEUSDTPERP": {
    "cycle_count": 128850,
    "current_phase": 0,
    "maker_account": "CM1",
    "maker_side": "BUY",
    "last_cycle_time": "2026-04-16T14:39:58.644013889+00:00",
    "total_trades": 128850,
    "external_fills": 0
  }
}