{
  "AVAXUSDTPERP": {
    "cycle_count": 132225,
    "current_phase": 1,
    "maker_account": "CM1",
    "maker_side": "BUY",
    "last_cycle_time": "2026-04-17T04:55:00.455527970+00:00",
    "total_trades": 132225,
    "external_fills": 0
  },
  "DOGEUSDTPERP": {
    "cycle_count": 132244,
    "current_phase": 1,
    "maker_account": "CM1",
    "maker_side": "BUY",
    "last_cycle_time": "2026-04-17T04:55:00.434159057+00:00",
    "total_trades": 132244,
    "external_fills": 0
  },
  "BTCUSDTPERP": {
    "cycle_count": 132238,
    "current_phase": 1,
    "maker_account": "CM1",
    "maker_side": "BUY",
    "last_cycle_time": "2026-04-17T04:55:00.411622995+00:00",
    "total_trades": 132238,
    "external_fills": 0
  },
  "SOLUSDTPERP": {
    "cycle_count": 132260,
    "current_phase": 0,
    "maker_account": "CM1",
    "maker_side": "BUY",
    "last_cycle_time": "2026-04-17T04:55:00.444620484+00:00",
    "total_trades": 132260,
    "external_fills": 0
  },
  "ETHUSDTPERP": {
    "cycle_count": 132248,
    "current_phase": 0,
    "maker_account": "CM1",
    "maker_side": "BUY",
    "last_cycle_time": "2026-04-17T04:55:00.422686666+00:00",
    "total_trades": 132248,
    "external_fills": 0
  },
  "XRPUSDTPERP": {
    "cycle_count": 132236,
    "current_phase": 0,
    "maker_account": "CM1",
    "maker_side": "BUY",
    "last_cycle_time": "2026-04-17T04:55:00.466495408+00:00",
    "total_trades": 132236,
    "external_fills": 0
  }
}