{
  "XRPUSDTPERP": {
    "cycle_count": 83676,
    "current_phase": 0,
    "maker_account": "CM1",
    "maker_side": "BUY",
    "last_cycle_time": "2026-04-08T14:39:51.346621438+00:00",
    "total_trades": 83676,
    "external_fills": 0
  },
  "AVAXUSDTPERP": {
    "cycle_count": 83667,
    "current_phase": 1,
    "maker_account": "CM1",
    "maker_side": "BUY",
    "last_cycle_time": "2026-04-08T14:39:51.327453074+00:00",
    "total_trades": 83667,
    "external_fills": 0
  },
  "ETHUSDTPERP": {
    "cycle_count": 83680,
    "current_phase": 1,
    "maker_account": "CM1",
    "maker_side": "BUY",
    "last_cycle_time": "2026-04-08T14:39:51.365829633+00:00",
    "total_trades": 83680,
    "external_fills": 0
  },
  "SOLUSDTPERP": {
    "cycle_count": 83706,
    "current_phase": 0,
    "maker_account": "CM1",
    "maker_side": "BUY",
    "last_cycle_time": "2026-04-08T14:39:51.337091941+00:00",
    "total_trades": 83706,
    "external_fills": 0
  },
  "DOGEUSDTPERP": {
    "cycle_count": 83681,
    "current_phase": 1,
    "maker_account": "CM1",
    "maker_side": "BUY",
    "last_cycle_time": "2026-04-08T14:39:51.375326666+00:00",
    "total_trades": 83681,
    "external_fills": 0
  },
  "BTCUSDTPERP": {
    "cycle_count": 83681,
    "current_phase": 1,
    "maker_account": "CM1",
    "maker_side": "BUY",
    "last_cycle_time": "2026-04-08T14:39:51.356299618+00:00",
    "total_trades": 83681,
    "external_fills": 0
  }
}