{
  "DOGEUSDTPERP": {
    "cycle_count": 130992,
    "current_phase": 0,
    "maker_account": "CM1",
    "maker_side": "BUY",
    "last_cycle_time": "2026-04-16T23:39:57.468645434+00:00",
    "total_trades": 130992,
    "external_fills": 0
  },
  "AVAXUSDTPERP": {
    "cycle_count": 130973,
    "current_phase": 1,
    "maker_account": "CM1",
    "maker_side": "BUY",
    "last_cycle_time": "2026-04-16T23:39:57.490764972+00:00",
    "total_trades": 130973,
    "external_fills": 0
  },
  "XRPUSDTPERP": {
    "cycle_count": 130984,
    "current_phase": 1,
    "maker_account": "CM1",
    "maker_side": "BUY",
    "last_cycle_time": "2026-04-16T23:39:57.501282196+00:00",
    "total_trades": 130984,
    "external_fills": 0
  },
  "SOLUSDTPERP": {
    "cycle_count": 131008,
    "current_phase": 1,
    "maker_account": "CM1",
    "maker_side": "BUY",
    "last_cycle_time": "2026-04-16T23:39:57.479607947+00:00",
    "total_trades": 131008,
    "external_fills": 0
  },
  "ETHUSDTPERP": {
    "cycle_count": 130996,
    "current_phase": 1,
    "maker_account": "CM1",
    "maker_side": "BUY",
    "last_cycle_time": "2026-04-16T23:39:57.457350634+00:00",
    "total_trades": 130996,
    "external_fills": 0
  },
  "BTCUSDTPERP": {
    "cycle_count": 130986,
    "current_phase": 0,
    "maker_account": "CM1",
    "maker_side": "BUY",
    "last_cycle_time": "2026-04-16T23:39:57.446425748+00:00",
    "total_trades": 130986,
    "external_fills": 0
  }
}