{
  "AVAXUSDTPERP": {
    "cycle_count": 114534,
    "current_phase": 0,
    "maker_account": "CM1",
    "maker_side": "BUY",
    "last_cycle_time": "2026-04-14T01:59:56.963249281+00:00",
    "total_trades": 114534,
    "external_fills": 0
  },
  "XRPUSDTPERP": {
    "cycle_count": 114543,
    "current_phase": 1,
    "maker_account": "CM1",
    "maker_side": "BUY",
    "last_cycle_time": "2026-04-14T01:59:56.992484647+00:00",
    "total_trades": 114543,
    "external_fills": 0
  },
  "ETHUSDTPERP": {
    "cycle_count": 114560,
    "current_phase": 0,
    "maker_account": "CM1",
    "maker_side": "BUY",
    "last_cycle_time": "2026-04-14T01:59:57.020419352+00:00",
    "total_trades": 114560,
    "external_fills": 0
  },
  "DOGEUSDTPERP": {
    "cycle_count": 114556,
    "current_phase": 1,
    "maker_account": "CM1",
    "maker_side": "BUY",
    "last_cycle_time": "2026-04-14T01:59:57.034590882+00:00",
    "total_trades": 114556,
    "external_fills": 0
  },
  "SOLUSDTPERP": {
    "cycle_count": 114571,
    "current_phase": 0,
    "maker_account": "CM1",
    "maker_side": "BUY",
    "last_cycle_time": "2026-04-14T01:59:56.978038345+00:00",
    "total_trades": 114571,
    "external_fills": 0
  },
  "BTCUSDTPERP": {
    "cycle_count": 114552,
    "current_phase": 0,
    "maker_account": "CM1",
    "maker_side": "BUY",
    "last_cycle_time": "2026-04-14T01:59:57.006789022+00:00",
    "total_trades": 114552,
    "external_fills": 0
  }
}