{
  "DOGEUSDTPERP": {
    "cycle_count": 134731,
    "current_phase": 0,
    "maker_account": "CM1",
    "maker_side": "BUY",
    "last_cycle_time": "2026-04-17T15:35:01.911538597+00:00",
    "total_trades": 134731,
    "external_fills": 0
  },
  "AVAXUSDTPERP": {
    "cycle_count": 134713,
    "current_phase": 0,
    "maker_account": "CM1",
    "maker_side": "BUY",
    "last_cycle_time": "2026-04-17T15:35:01.936981919+00:00",
    "total_trades": 134713,
    "external_fills": 0
  },
  "XRPUSDTPERP": {
    "cycle_count": 134725,
    "current_phase": 0,
    "maker_account": "CM1",
    "maker_side": "BUY",
    "last_cycle_time": "2026-04-17T15:35:01.952617210+00:00",
    "total_trades": 134725,
    "external_fills": 0
  },
  "ETHUSDTPERP": {
    "cycle_count": 134734,
    "current_phase": 1,
    "maker_account": "CM1",
    "maker_side": "BUY",
    "last_cycle_time": "2026-04-17T15:35:01.897607768+00:00",
    "total_trades": 134734,
    "external_fills": 0
  },
  "SOLUSDTPERP": {
    "cycle_count": 134747,
    "current_phase": 1,
    "maker_account": "CM1",
    "maker_side": "BUY",
    "last_cycle_time": "2026-04-17T15:35:01.925620024+00:00",
    "total_trades": 134747,
    "external_fills": 0
  },
  "BTCUSDTPERP": {
    "cycle_count": 134724,
    "current_phase": 0,
    "maker_account": "CM1",
    "maker_side": "BUY",
    "last_cycle_time": "2026-04-17T15:35:01.881297290+00:00",
    "total_trades": 134724,
    "external_fills": 0
  }
}