{
  "TSLAXUSDT": {
    "cycle_count": 107525,
    "total_trades": 107525
  },
  "BITGOLDUSDT": {
    "cycle_count": 107511,
    "total_trades": 107511
  },
  "SOLZAR": {
    "cycle_count": 843,
    "total_trades": 843
  },
  "MSTRXUSDT": {
    "cycle_count": 107519,
    "total_trades": 107519
  },
  "EURCUSDC": {
    "cycle_count": 107498,
    "total_trades": 107498
  },
  "TRUMPUSDT": {
    "cycle_count": 107504,
    "total_trades": 107504
  },
  "SPYXUSDT": {
    "cycle_count": 107507,
    "total_trades": 107507
  },
  "AVAXZAR": {
    "cycle_count": 842,
    "total_trades": 842
  },
  "USDCZAR": {
    "cycle_count": 831,
    "total_trades": 831
  },
  "HOODXUSDT": {
    "cycle_count": 107515,
    "total_trades": 107515
  },
  "CRCLXUSDT": {
    "cycle_count": 107504,
    "total_trades": 107504
  },
  "NVDAXUSDT": {
    "cycle_count": 107514,
    "total_trades": 107514
  },
  "ETHZAR": {
    "cycle_count": 843,
    "total_trades": 843
  },
  "USDPCUSDT": {
    "cycle_count": 29853,
    "total_trades": 29853
  },
  "BNBZAR": {
    "cycle_count": 844,
    "total_trades": 844
  },
  "VALR10USDT": {
    "cycle_count": 107519,
    "total_trades": 107519
  },
  "JUPUSDT": {
    "cycle_count": 107500,
    "total_trades": 107500
  },
  "COINXUSDT": {
    "cycle_count": 107521,
    "total_trades": 107521
  },
  "XRPZAR": {
    "cycle_count": 844,
    "total_trades": 844
  },
  "XAUTUSDT": {
    "cycle_count": 869,
    "total_trades": 869
  },
  "XAUTZAR": {
    "cycle_count": 832,
    "total_trades": 832
  },
  "BTCZAR": {
    "cycle_count": 842,
    "total_trades": 842
  },
  "LINKZAR": {
    "cycle_count": 844,
    "total_trades": 844
  }
}