{
  "JUPUSDT": {
    "cycle_count": 70399,
    "total_trades": 70399
  },
  "TRUMPUSDT": {
    "cycle_count": 70403,
    "total_trades": 70403
  },
  "SPYXUSDT": {
    "cycle_count": 70414,
    "total_trades": 70414
  },
  "VALR10USDT": {
    "cycle_count": 70418,
    "total_trades": 70418
  },
  "EURCUSDC": {
    "cycle_count": 70402,
    "total_trades": 70402
  },
  "USDPCUSDT": {
    "cycle_count": 29853,
    "total_trades": 29853
  },
  "HOODXUSDT": {
    "cycle_count": 70414,
    "total_trades": 70414
  },
  "BITGOLDUSDT": {
    "cycle_count": 70417,
    "total_trades": 70417
  },
  "COINXUSDT": {
    "cycle_count": 70419,
    "total_trades": 70419
  },
  "MSTRXUSDT": {
    "cycle_count": 70418,
    "total_trades": 70418
  },
  "CRCLXUSDT": {
    "cycle_count": 70414,
    "total_trades": 70414
  },
  "TSLAXUSDT": {
    "cycle_count": 70422,
    "total_trades": 70422
  },
  "NVDAXUSDT": {
    "cycle_count": 70415,
    "total_trades": 70415
  }
}