{
  "TSLAXUSDT": {
    "cycle_count": 108195,
    "total_trades": 108195
  },
  "BITGOLDUSDT": {
    "cycle_count": 108179,
    "total_trades": 108179
  },
  "SOLZAR": {
    "cycle_count": 1512,
    "total_trades": 1512
  },
  "MSTRXUSDT": {
    "cycle_count": 108188,
    "total_trades": 108188
  },
  "EURCUSDC": {
    "cycle_count": 108168,
    "total_trades": 108168
  },
  "TRUMPUSDT": {
    "cycle_count": 108173,
    "total_trades": 108173
  },
  "SPYXUSDT": {
    "cycle_count": 108177,
    "total_trades": 108177
  },
  "AVAXZAR": {
    "cycle_count": 1511,
    "total_trades": 1511
  },
  "USDCZAR": {
    "cycle_count": 1501,
    "total_trades": 1501
  },
  "HOODXUSDT": {
    "cycle_count": 108184,
    "total_trades": 108184
  },
  "CRCLXUSDT": {
    "cycle_count": 108173,
    "total_trades": 108173
  },
  "NVDAXUSDT": {
    "cycle_count": 108184,
    "total_trades": 108184
  },
  "ETHZAR": {
    "cycle_count": 1513,
    "total_trades": 1513
  },
  "USDPCUSDT": {
    "cycle_count": 29853,
    "total_trades": 29853
  },
  "BNBZAR": {
    "cycle_count": 1513,
    "total_trades": 1513
  },
  "VALR10USDT": {
    "cycle_count": 108189,
    "total_trades": 108189
  },
  "JUPUSDT": {
    "cycle_count": 108168,
    "total_trades": 108168
  },
  "COINXUSDT": {
    "cycle_count": 108191,
    "total_trades": 108191
  },
  "XRPZAR": {
    "cycle_count": 1514,
    "total_trades": 1514
  },
  "XAUTUSDT": {
    "cycle_count": 1538,
    "total_trades": 1538
  },
  "XAUTZAR": {
    "cycle_count": 1501,
    "total_trades": 1501
  },
  "BTCZAR": {
    "cycle_count": 1512,
    "total_trades": 1512
  },
  "LINKZAR": {
    "cycle_count": 1514,
    "total_trades": 1514
  }
}