{
  "JUPUSDT": {
    "cycle_count": 74435,
    "total_trades": 74435
  },
  "TRUMPUSDT": {
    "cycle_count": 74438,
    "total_trades": 74438
  },
  "SPYXUSDT": {
    "cycle_count": 74447,
    "total_trades": 74447
  },
  "VALR10USDT": {
    "cycle_count": 74453,
    "total_trades": 74453
  },
  "EURCUSDC": {
    "cycle_count": 74436,
    "total_trades": 74436
  },
  "USDPCUSDT": {
    "cycle_count": 29853,
    "total_trades": 29853
  },
  "HOODXUSDT": {
    "cycle_count": 74450,
    "total_trades": 74450
  },
  "BITGOLDUSDT": {
    "cycle_count": 74449,
    "total_trades": 74449
  },
  "COINXUSDT": {
    "cycle_count": 74455,
    "total_trades": 74455
  },
  "MSTRXUSDT": {
    "cycle_count": 74452,
    "total_trades": 74452
  },
  "CRCLXUSDT": {
    "cycle_count": 74446,
    "total_trades": 74446
  },
  "TSLAXUSDT": {
    "cycle_count": 74457,
    "total_trades": 74457
  },
  "NVDAXUSDT": {
    "cycle_count": 74449,
    "total_trades": 74449
  }
}