{
  "JUPUSDT": {
    "cycle_count": 100704,
    "total_trades": 100704
  },
  "TRUMPUSDT": {
    "cycle_count": 100710,
    "total_trades": 100710
  },
  "SPYXUSDT": {
    "cycle_count": 100715,
    "total_trades": 100715
  },
  "VALR10USDT": {
    "cycle_count": 100725,
    "total_trades": 100725
  },
  "EURCUSDC": {
    "cycle_count": 100704,
    "total_trades": 100704
  },
  "USDPCUSDT": {
    "cycle_count": 29853,
    "total_trades": 29853
  },
  "HOODXUSDT": {
    "cycle_count": 100720,
    "total_trades": 100720
  },
  "BITGOLDUSDT": {
    "cycle_count": 100718,
    "total_trades": 100718
  },
  "COINXUSDT": {
    "cycle_count": 100725,
    "total_trades": 100725
  },
  "MSTRXUSDT": {
    "cycle_count": 100725,
    "total_trades": 100725
  },
  "CRCLXUSDT": {
    "cycle_count": 100714,
    "total_trades": 100714
  },
  "TSLAXUSDT": {
    "cycle_count": 100731,
    "total_trades": 100731
  },
  "NVDAXUSDT": {
    "cycle_count": 100720,
    "total_trades": 100720
  }
}