{
  "JUPUSDT": {
    "cycle_count": 99154,
    "total_trades": 99154
  },
  "TRUMPUSDT": {
    "cycle_count": 99160,
    "total_trades": 99160
  },
  "SPYXUSDT": {
    "cycle_count": 99164,
    "total_trades": 99164
  },
  "VALR10USDT": {
    "cycle_count": 99175,
    "total_trades": 99175
  },
  "EURCUSDC": {
    "cycle_count": 99153,
    "total_trades": 99153
  },
  "USDPCUSDT": {
    "cycle_count": 29853,
    "total_trades": 29853
  },
  "HOODXUSDT": {
    "cycle_count": 99170,
    "total_trades": 99170
  },
  "BITGOLDUSDT": {
    "cycle_count": 99167,
    "total_trades": 99167
  },
  "COINXUSDT": {
    "cycle_count": 99175,
    "total_trades": 99175
  },
  "MSTRXUSDT": {
    "cycle_count": 99175,
    "total_trades": 99175
  },
  "CRCLXUSDT": {
    "cycle_count": 99163,
    "total_trades": 99163
  },
  "TSLAXUSDT": {
    "cycle_count": 99181,
    "total_trades": 99181
  },
  "NVDAXUSDT": {
    "cycle_count": 99169,
    "total_trades": 99169
  }
}