{
  "JUPUSDT": {
    "cycle_count": 75300,
    "total_trades": 75300
  },
  "TRUMPUSDT": {
    "cycle_count": 75303,
    "total_trades": 75303
  },
  "SPYXUSDT": {
    "cycle_count": 75311,
    "total_trades": 75311
  },
  "VALR10USDT": {
    "cycle_count": 75318,
    "total_trades": 75318
  },
  "EURCUSDC": {
    "cycle_count": 75300,
    "total_trades": 75300
  },
  "USDPCUSDT": {
    "cycle_count": 29853,
    "total_trades": 29853
  },
  "HOODXUSDT": {
    "cycle_count": 75315,
    "total_trades": 75315
  },
  "BITGOLDUSDT": {
    "cycle_count": 75314,
    "total_trades": 75314
  },
  "COINXUSDT": {
    "cycle_count": 75320,
    "total_trades": 75320
  },
  "MSTRXUSDT": {
    "cycle_count": 75316,
    "total_trades": 75316
  },
  "CRCLXUSDT": {
    "cycle_count": 75310,
    "total_trades": 75310
  },
  "TSLAXUSDT": {
    "cycle_count": 75321,
    "total_trades": 75321
  },
  "NVDAXUSDT": {
    "cycle_count": 75314,
    "total_trades": 75314
  }
}