{
  "JUPUSDT": {
    "cycle_count": 74056,
    "total_trades": 74056
  },
  "TRUMPUSDT": {
    "cycle_count": 74060,
    "total_trades": 74060
  },
  "SPYXUSDT": {
    "cycle_count": 74069,
    "total_trades": 74069
  },
  "VALR10USDT": {
    "cycle_count": 74075,
    "total_trades": 74075
  },
  "EURCUSDC": {
    "cycle_count": 74057,
    "total_trades": 74057
  },
  "USDPCUSDT": {
    "cycle_count": 29853,
    "total_trades": 29853
  },
  "HOODXUSDT": {
    "cycle_count": 74071,
    "total_trades": 74071
  },
  "BITGOLDUSDT": {
    "cycle_count": 74072,
    "total_trades": 74072
  },
  "COINXUSDT": {
    "cycle_count": 74076,
    "total_trades": 74076
  },
  "MSTRXUSDT": {
    "cycle_count": 74075,
    "total_trades": 74075
  },
  "CRCLXUSDT": {
    "cycle_count": 74069,
    "total_trades": 74069
  },
  "TSLAXUSDT": {
    "cycle_count": 74079,
    "total_trades": 74079
  },
  "NVDAXUSDT": {
    "cycle_count": 74071,
    "total_trades": 74071
  }
}