{
  "TSLAXUSDT": {
    "cycle_count": 108733,
    "total_trades": 108733
  },
  "BITGOLDUSDT": {
    "cycle_count": 108719,
    "total_trades": 108719
  },
  "SOLZAR": {
    "cycle_count": 2051,
    "total_trades": 2051
  },
  "MSTRXUSDT": {
    "cycle_count": 108728,
    "total_trades": 108728
  },
  "EURCUSDC": {
    "cycle_count": 108705,
    "total_trades": 108705
  },
  "TRUMPUSDT": {
    "cycle_count": 108713,
    "total_trades": 108713
  },
  "SPYXUSDT": {
    "cycle_count": 108716,
    "total_trades": 108716
  },
  "AVAXZAR": {
    "cycle_count": 2047,
    "total_trades": 2047
  },
  "USDCZAR": {
    "cycle_count": 2040,
    "total_trades": 2040
  },
  "HOODXUSDT": {
    "cycle_count": 108724,
    "total_trades": 108724
  },
  "CRCLXUSDT": {
    "cycle_count": 108711,
    "total_trades": 108711
  },
  "NVDAXUSDT": {
    "cycle_count": 108722,
    "total_trades": 108722
  },
  "ETHZAR": {
    "cycle_count": 2051,
    "total_trades": 2051
  },
  "USDPCUSDT": {
    "cycle_count": 29853,
    "total_trades": 29853
  },
  "BNBZAR": {
    "cycle_count": 2053,
    "total_trades": 2053
  },
  "VALR10USDT": {
    "cycle_count": 108727,
    "total_trades": 108727
  },
  "JUPUSDT": {
    "cycle_count": 108707,
    "total_trades": 108707
  },
  "COINXUSDT": {
    "cycle_count": 108730,
    "total_trades": 108730
  },
  "XRPZAR": {
    "cycle_count": 2052,
    "total_trades": 2052
  },
  "XAUTUSDT": {
    "cycle_count": 2076,
    "total_trades": 2076
  },
  "XAUTZAR": {
    "cycle_count": 2041,
    "total_trades": 2041
  },
  "BTCZAR": {
    "cycle_count": 2051,
    "total_trades": 2051
  },
  "LINKZAR": {
    "cycle_count": 2054,
    "total_trades": 2054
  }
}