{
  "TSLAXUSDT": {
    "cycle_count": 108675,
    "total_trades": 108675
  },
  "BITGOLDUSDT": {
    "cycle_count": 108661,
    "total_trades": 108661
  },
  "SOLZAR": {
    "cycle_count": 1993,
    "total_trades": 1993
  },
  "MSTRXUSDT": {
    "cycle_count": 108670,
    "total_trades": 108670
  },
  "EURCUSDC": {
    "cycle_count": 108647,
    "total_trades": 108647
  },
  "TRUMPUSDT": {
    "cycle_count": 108655,
    "total_trades": 108655
  },
  "SPYXUSDT": {
    "cycle_count": 108658,
    "total_trades": 108658
  },
  "AVAXZAR": {
    "cycle_count": 1989,
    "total_trades": 1989
  },
  "USDCZAR": {
    "cycle_count": 1982,
    "total_trades": 1982
  },
  "HOODXUSDT": {
    "cycle_count": 108666,
    "total_trades": 108666
  },
  "CRCLXUSDT": {
    "cycle_count": 108653,
    "total_trades": 108653
  },
  "NVDAXUSDT": {
    "cycle_count": 108664,
    "total_trades": 108664
  },
  "ETHZAR": {
    "cycle_count": 1993,
    "total_trades": 1993
  },
  "USDPCUSDT": {
    "cycle_count": 29853,
    "total_trades": 29853
  },
  "BNBZAR": {
    "cycle_count": 1995,
    "total_trades": 1995
  },
  "VALR10USDT": {
    "cycle_count": 108669,
    "total_trades": 108669
  },
  "JUPUSDT": {
    "cycle_count": 108649,
    "total_trades": 108649
  },
  "COINXUSDT": {
    "cycle_count": 108672,
    "total_trades": 108672
  },
  "XRPZAR": {
    "cycle_count": 1994,
    "total_trades": 1994
  },
  "XAUTUSDT": {
    "cycle_count": 2018,
    "total_trades": 2018
  },
  "XAUTZAR": {
    "cycle_count": 1983,
    "total_trades": 1983
  },
  "BTCZAR": {
    "cycle_count": 1993,
    "total_trades": 1993
  },
  "LINKZAR": {
    "cycle_count": 1996,
    "total_trades": 1996
  }
}