{
  "JUPUSDT": {
    "cycle_count": 101524,
    "total_trades": 101524
  },
  "TRUMPUSDT": {
    "cycle_count": 101530,
    "total_trades": 101530
  },
  "SPYXUSDT": {
    "cycle_count": 101534,
    "total_trades": 101534
  },
  "VALR10USDT": {
    "cycle_count": 101545,
    "total_trades": 101545
  },
  "EURCUSDC": {
    "cycle_count": 101523,
    "total_trades": 101523
  },
  "USDPCUSDT": {
    "cycle_count": 29853,
    "total_trades": 29853
  },
  "HOODXUSDT": {
    "cycle_count": 101540,
    "total_trades": 101540
  },
  "BITGOLDUSDT": {
    "cycle_count": 101537,
    "total_trades": 101537
  },
  "COINXUSDT": {
    "cycle_count": 101545,
    "total_trades": 101545
  },
  "MSTRXUSDT": {
    "cycle_count": 101545,
    "total_trades": 101545
  },
  "CRCLXUSDT": {
    "cycle_count": 101533,
    "total_trades": 101533
  },
  "TSLAXUSDT": {
    "cycle_count": 101551,
    "total_trades": 101551
  },
  "NVDAXUSDT": {
    "cycle_count": 101539,
    "total_trades": 101539
  }
}