{
  "JUPUSDT": {
    "cycle_count": 75621,
    "total_trades": 75621
  },
  "TRUMPUSDT": {
    "cycle_count": 75624,
    "total_trades": 75624
  },
  "SPYXUSDT": {
    "cycle_count": 75632,
    "total_trades": 75632
  },
  "VALR10USDT": {
    "cycle_count": 75639,
    "total_trades": 75639
  },
  "EURCUSDC": {
    "cycle_count": 75621,
    "total_trades": 75621
  },
  "USDPCUSDT": {
    "cycle_count": 29853,
    "total_trades": 29853
  },
  "HOODXUSDT": {
    "cycle_count": 75636,
    "total_trades": 75636
  },
  "BITGOLDUSDT": {
    "cycle_count": 75635,
    "total_trades": 75635
  },
  "COINXUSDT": {
    "cycle_count": 75641,
    "total_trades": 75641
  },
  "MSTRXUSDT": {
    "cycle_count": 75637,
    "total_trades": 75637
  },
  "CRCLXUSDT": {
    "cycle_count": 75631,
    "total_trades": 75631
  },
  "TSLAXUSDT": {
    "cycle_count": 75642,
    "total_trades": 75642
  },
  "NVDAXUSDT": {
    "cycle_count": 75635,
    "total_trades": 75635
  }
}