{
  "JUPUSDT": {
    "cycle_count": 82045,
    "total_trades": 82045
  },
  "TRUMPUSDT": {
    "cycle_count": 82049,
    "total_trades": 82049
  },
  "SPYXUSDT": {
    "cycle_count": 82055,
    "total_trades": 82055
  },
  "VALR10USDT": {
    "cycle_count": 82063,
    "total_trades": 82063
  },
  "EURCUSDC": {
    "cycle_count": 82044,
    "total_trades": 82044
  },
  "USDPCUSDT": {
    "cycle_count": 29853,
    "total_trades": 29853
  },
  "HOODXUSDT": {
    "cycle_count": 82060,
    "total_trades": 82060
  },
  "BITGOLDUSDT": {
    "cycle_count": 82058,
    "total_trades": 82058
  },
  "COINXUSDT": {
    "cycle_count": 82065,
    "total_trades": 82065
  },
  "MSTRXUSDT": {
    "cycle_count": 82062,
    "total_trades": 82062
  },
  "CRCLXUSDT": {
    "cycle_count": 82054,
    "total_trades": 82054
  },
  "TSLAXUSDT": {
    "cycle_count": 82068,
    "total_trades": 82068
  },
  "NVDAXUSDT": {
    "cycle_count": 82059,
    "total_trades": 82059
  }
}