{
  "JUPUSDT": {
    "cycle_count": 98162,
    "total_trades": 98162
  },
  "TRUMPUSDT": {
    "cycle_count": 98168,
    "total_trades": 98168
  },
  "SPYXUSDT": {
    "cycle_count": 98172,
    "total_trades": 98172
  },
  "VALR10USDT": {
    "cycle_count": 98183,
    "total_trades": 98183
  },
  "EURCUSDC": {
    "cycle_count": 98161,
    "total_trades": 98161
  },
  "USDPCUSDT": {
    "cycle_count": 29853,
    "total_trades": 29853
  },
  "HOODXUSDT": {
    "cycle_count": 98178,
    "total_trades": 98178
  },
  "BITGOLDUSDT": {
    "cycle_count": 98175,
    "total_trades": 98175
  },
  "COINXUSDT": {
    "cycle_count": 98183,
    "total_trades": 98183
  },
  "MSTRXUSDT": {
    "cycle_count": 98183,
    "total_trades": 98183
  },
  "CRCLXUSDT": {
    "cycle_count": 98171,
    "total_trades": 98171
  },
  "TSLAXUSDT": {
    "cycle_count": 98189,
    "total_trades": 98189
  },
  "NVDAXUSDT": {
    "cycle_count": 98177,
    "total_trades": 98177
  }
}