{
  "JUPUSDT": {
    "cycle_count": 79066,
    "total_trades": 79066
  },
  "TRUMPUSDT": {
    "cycle_count": 79070,
    "total_trades": 79070
  },
  "SPYXUSDT": {
    "cycle_count": 79077,
    "total_trades": 79077
  },
  "VALR10USDT": {
    "cycle_count": 79085,
    "total_trades": 79085
  },
  "EURCUSDC": {
    "cycle_count": 79066,
    "total_trades": 79066
  },
  "USDPCUSDT": {
    "cycle_count": 29853,
    "total_trades": 29853
  },
  "HOODXUSDT": {
    "cycle_count": 79081,
    "total_trades": 79081
  },
  "BITGOLDUSDT": {
    "cycle_count": 79080,
    "total_trades": 79080
  },
  "COINXUSDT": {
    "cycle_count": 79086,
    "total_trades": 79086
  },
  "MSTRXUSDT": {
    "cycle_count": 79084,
    "total_trades": 79084
  },
  "CRCLXUSDT": {
    "cycle_count": 79076,
    "total_trades": 79076
  },
  "TSLAXUSDT": {
    "cycle_count": 79089,
    "total_trades": 79089
  },
  "NVDAXUSDT": {
    "cycle_count": 79080,
    "total_trades": 79080
  }
}