{
  "JUPUSDT": {
    "cycle_count": 69231,
    "total_trades": 69231
  },
  "TRUMPUSDT": {
    "cycle_count": 69233,
    "total_trades": 69233
  },
  "SPYXUSDT": {
    "cycle_count": 69245,
    "total_trades": 69245
  },
  "VALR10USDT": {
    "cycle_count": 69248,
    "total_trades": 69248
  },
  "EURCUSDC": {
    "cycle_count": 69233,
    "total_trades": 69233
  },
  "USDPCUSDT": {
    "cycle_count": 29853,
    "total_trades": 29853
  },
  "HOODXUSDT": {
    "cycle_count": 69245,
    "total_trades": 69245
  },
  "BITGOLDUSDT": {
    "cycle_count": 69247,
    "total_trades": 69247
  },
  "COINXUSDT": {
    "cycle_count": 69249,
    "total_trades": 69249
  },
  "MSTRXUSDT": {
    "cycle_count": 69248,
    "total_trades": 69248
  },
  "CRCLXUSDT": {
    "cycle_count": 69245,
    "total_trades": 69245
  },
  "TSLAXUSDT": {
    "cycle_count": 69251,
    "total_trades": 69251
  },
  "NVDAXUSDT": {
    "cycle_count": 69247,
    "total_trades": 69247
  }
}