{
  "JUPUSDT": {
    "cycle_count": 89513,
    "total_trades": 89513
  },
  "TRUMPUSDT": {
    "cycle_count": 89517,
    "total_trades": 89517
  },
  "SPYXUSDT": {
    "cycle_count": 89522,
    "total_trades": 89522
  },
  "VALR10USDT": {
    "cycle_count": 89532,
    "total_trades": 89532
  },
  "EURCUSDC": {
    "cycle_count": 89511,
    "total_trades": 89511
  },
  "USDPCUSDT": {
    "cycle_count": 29853,
    "total_trades": 29853
  },
  "HOODXUSDT": {
    "cycle_count": 89528,
    "total_trades": 89528
  },
  "BITGOLDUSDT": {
    "cycle_count": 89525,
    "total_trades": 89525
  },
  "COINXUSDT": {
    "cycle_count": 89533,
    "total_trades": 89533
  },
  "MSTRXUSDT": {
    "cycle_count": 89531,
    "total_trades": 89531
  },
  "CRCLXUSDT": {
    "cycle_count": 89521,
    "total_trades": 89521
  },
  "TSLAXUSDT": {
    "cycle_count": 89537,
    "total_trades": 89537
  },
  "NVDAXUSDT": {
    "cycle_count": 89527,
    "total_trades": 89527
  }
}