{
  "JUPUSDT": {
    "cycle_count": 97147,
    "total_trades": 97147
  },
  "TRUMPUSDT": {
    "cycle_count": 97153,
    "total_trades": 97153
  },
  "SPYXUSDT": {
    "cycle_count": 97157,
    "total_trades": 97157
  },
  "VALR10USDT": {
    "cycle_count": 97168,
    "total_trades": 97168
  },
  "EURCUSDC": {
    "cycle_count": 97146,
    "total_trades": 97146
  },
  "USDPCUSDT": {
    "cycle_count": 29853,
    "total_trades": 29853
  },
  "HOODXUSDT": {
    "cycle_count": 97163,
    "total_trades": 97163
  },
  "BITGOLDUSDT": {
    "cycle_count": 97160,
    "total_trades": 97160
  },
  "COINXUSDT": {
    "cycle_count": 97168,
    "total_trades": 97168
  },
  "MSTRXUSDT": {
    "cycle_count": 97168,
    "total_trades": 97168
  },
  "CRCLXUSDT": {
    "cycle_count": 97156,
    "total_trades": 97156
  },
  "TSLAXUSDT": {
    "cycle_count": 97174,
    "total_trades": 97174
  },
  "NVDAXUSDT": {
    "cycle_count": 97162,
    "total_trades": 97162
  }
}