{
  "JUPUSDT": {
    "cycle_count": 82691,
    "total_trades": 82691
  },
  "TRUMPUSDT": {
    "cycle_count": 82695,
    "total_trades": 82695
  },
  "SPYXUSDT": {
    "cycle_count": 82701,
    "total_trades": 82701
  },
  "VALR10USDT": {
    "cycle_count": 82709,
    "total_trades": 82709
  },
  "EURCUSDC": {
    "cycle_count": 82690,
    "total_trades": 82690
  },
  "USDPCUSDT": {
    "cycle_count": 29853,
    "total_trades": 29853
  },
  "HOODXUSDT": {
    "cycle_count": 82706,
    "total_trades": 82706
  },
  "BITGOLDUSDT": {
    "cycle_count": 82704,
    "total_trades": 82704
  },
  "COINXUSDT": {
    "cycle_count": 82711,
    "total_trades": 82711
  },
  "MSTRXUSDT": {
    "cycle_count": 82708,
    "total_trades": 82708
  },
  "CRCLXUSDT": {
    "cycle_count": 82700,
    "total_trades": 82700
  },
  "TSLAXUSDT": {
    "cycle_count": 82714,
    "total_trades": 82714
  },
  "NVDAXUSDT": {
    "cycle_count": 82705,
    "total_trades": 82705
  }
}