{
  "JUPUSDT": {
    "cycle_count": 77713,
    "total_trades": 77713
  },
  "TRUMPUSDT": {
    "cycle_count": 77717,
    "total_trades": 77717
  },
  "SPYXUSDT": {
    "cycle_count": 77724,
    "total_trades": 77724
  },
  "VALR10USDT": {
    "cycle_count": 77732,
    "total_trades": 77732
  },
  "EURCUSDC": {
    "cycle_count": 77713,
    "total_trades": 77713
  },
  "USDPCUSDT": {
    "cycle_count": 29853,
    "total_trades": 29853
  },
  "HOODXUSDT": {
    "cycle_count": 77728,
    "total_trades": 77728
  },
  "BITGOLDUSDT": {
    "cycle_count": 77727,
    "total_trades": 77727
  },
  "COINXUSDT": {
    "cycle_count": 77733,
    "total_trades": 77733
  },
  "MSTRXUSDT": {
    "cycle_count": 77731,
    "total_trades": 77731
  },
  "CRCLXUSDT": {
    "cycle_count": 77723,
    "total_trades": 77723
  },
  "TSLAXUSDT": {
    "cycle_count": 77736,
    "total_trades": 77736
  },
  "NVDAXUSDT": {
    "cycle_count": 77727,
    "total_trades": 77727
  }
}