{
  "JUPUSDT": {
    "cycle_count": 78374,
    "total_trades": 78374
  },
  "TRUMPUSDT": {
    "cycle_count": 78378,
    "total_trades": 78378
  },
  "SPYXUSDT": {
    "cycle_count": 78385,
    "total_trades": 78385
  },
  "VALR10USDT": {
    "cycle_count": 78393,
    "total_trades": 78393
  },
  "EURCUSDC": {
    "cycle_count": 78374,
    "total_trades": 78374
  },
  "USDPCUSDT": {
    "cycle_count": 29853,
    "total_trades": 29853
  },
  "HOODXUSDT": {
    "cycle_count": 78389,
    "total_trades": 78389
  },
  "BITGOLDUSDT": {
    "cycle_count": 78388,
    "total_trades": 78388
  },
  "COINXUSDT": {
    "cycle_count": 78394,
    "total_trades": 78394
  },
  "MSTRXUSDT": {
    "cycle_count": 78392,
    "total_trades": 78392
  },
  "CRCLXUSDT": {
    "cycle_count": 78384,
    "total_trades": 78384
  },
  "TSLAXUSDT": {
    "cycle_count": 78397,
    "total_trades": 78397
  },
  "NVDAXUSDT": {
    "cycle_count": 78388,
    "total_trades": 78388
  }
}