{
  "JUPUSDT": {
    "cycle_count": 81397,
    "total_trades": 81397
  },
  "TRUMPUSDT": {
    "cycle_count": 81400,
    "total_trades": 81400
  },
  "SPYXUSDT": {
    "cycle_count": 81408,
    "total_trades": 81408
  },
  "VALR10USDT": {
    "cycle_count": 81414,
    "total_trades": 81414
  },
  "EURCUSDC": {
    "cycle_count": 81397,
    "total_trades": 81397
  },
  "USDPCUSDT": {
    "cycle_count": 29853,
    "total_trades": 29853
  },
  "HOODXUSDT": {
    "cycle_count": 81411,
    "total_trades": 81411
  },
  "BITGOLDUSDT": {
    "cycle_count": 81411,
    "total_trades": 81411
  },
  "COINXUSDT": {
    "cycle_count": 81416,
    "total_trades": 81416
  },
  "MSTRXUSDT": {
    "cycle_count": 81413,
    "total_trades": 81413
  },
  "CRCLXUSDT": {
    "cycle_count": 81407,
    "total_trades": 81407
  },
  "TSLAXUSDT": {
    "cycle_count": 81419,
    "total_trades": 81419
  },
  "NVDAXUSDT": {
    "cycle_count": 81411,
    "total_trades": 81411
  }
}